EmojiConvert.py
__init__.py
emojiconvert-0.0.1.dist-info/METADATA
emojiconvert-0.0.1.dist-info/WHEEL
emojiconvert-0.0.1.dist-info/entry_points.txt
emojiconvert-0.0.1.dist-info/licenses/LICENSE
emojiconvert-0.0.1.dist-info/RECORD
